<annotation>
	<folder>JPEGImages</folder>
	<filename>002763.jpg</filename>
	<path>VOC2007/JPEGImages/002763.jpg</path>
	<source>
		<database>Unknown</database>
	</source>
	<size>
		<width>1920</width>
		<height>1080</height>
		<depth>3</depth>
	</size>
	<segmented>0</segmented>
	<object>
		<name>fishing boat</name>
		<pose>Unspecified</pose>
		<truncated>1</truncated>
		<bndbox>
			<xmin>1397</xmin>
			<ymin>295</ymin>
			<xmax>1920</xmax>
			<ymax>486</ymax>
		</bndbox>
	</object>
	<object>
		<name>fishing boat</name>
		<pose>Unspecified</pose>
		<truncated>1</truncated>
		<bndbox>
			<xmin>1</xmin>
			<ymin>382</ymin>
			<xmax>459</xmax>
			<ymax>513</ymax>
		</bndbox>
	</object>
</annotation>
