<annotation>
	<folder>JPEGImages</folder>
	<filename>004744.jpg</filename>
	<path>VOC2007/JPEGImages/004744.jpg</path>
	<source>
		<database>Unknown</database>
	</source>
	<size>
		<width>1920</width>
		<height>1080</height>
		<depth>3</depth>
	</size>
	<segmented>0</segmented>
	<object>
		<name>fishing boat</name>
		<pose>Unspecified</pose>
		<truncated>0</truncated>
		<bndbox>
			<xmin>369</xmin>
			<ymin>564</ymin>
			<xmax>509</xmax>
			<ymax>594</ymax>
		</bndbox>
	</object>
	<object>
		<name>fishing boat</name>
		<pose>Unspecified</pose>
		<truncated>0</truncated>
		<bndbox>
			<xmin>705</xmin>
			<ymin>554</ymin>
			<xmax>837</xmax>
			<ymax>592</ymax>
		</bndbox>
	</object>
	<object>
		<name>fishing boat</name>
		<pose>Unspecified</pose>
		<truncated>0</truncated>
		<bndbox>
			<xmin>1009</xmin>
			<ymin>466</ymin>
			<xmax>1149</xmax>
			<ymax>498</ymax>
		</bndbox>
	</object>
	<object>
		<name>general cargo ship</name>
		<pose>Unspecified</pose>
		<truncated>1</truncated>
		<bndbox>
			<xmin>1</xmin>
			<ymin>126</ymin>
			<xmax>797</xmax>
			<ymax>474</ymax>
		</bndbox>
	</object>
</annotation>
