<annotation>
	<folder>JPEGImages</folder>
	<filename>004725.jpg</filename>
	<path>VOC2007/JPEGImages/004725.jpg</path>
	<source>
		<database>Unknown</database>
	</source>
	<size>
		<width>1920</width>
		<height>1080</height>
		<depth>3</depth>
	</size>
	<segmented>0</segmented>
	<object>
		<name>fishing boat</name>
		<pose>Unspecified</pose>
		<truncated>0</truncated>
		<bndbox>
			<xmin>479</xmin>
			<ymin>370</ymin>
			<xmax>705</xmax>
			<ymax>402</ymax>
		</bndbox>
	</object>
	<object>
		<name>general cargo ship</name>
		<pose>Unspecified</pose>
		<truncated>1</truncated>
		<bndbox>
			<xmin>1007</xmin>
			<ymin>222</ymin>
			<xmax>1920</xmax>
			<ymax>493</ymax>
		</bndbox>
	</object>
</annotation>
